dht_to_gbq/__init__.py
dht22_to_gbq-0.1.1.dist-info/entry_points.txt
dht22_to_gbq-0.1.1.dist-info/LICENSE
dht22_to_gbq-0.1.1.dist-info/WHEEL
dht22_to_gbq-0.1.1.dist-info/METADATA
dht22_to_gbq-0.1.1.dist-info/RECORD
